LICENSE
s4sdk/__init__.py
s4sdk/metadata.py
s4sdk/package/__init__.py
s4sdk/package/abstractpackage.py
s4sdk/package/dbpf.py
s4sdk/package/dirpackage.py
s4sdk/package/metapackage.py
s4sdk/resource/__init__.py
s4sdk/resource/abc.py
s4sdk/resource/binary.py
s4sdk/resource/stbl.py
s4sdk/utils.py
s4sdk-0.2.1a2.dist-info/LICENSE
s4sdk-0.2.1a2.dist-info/WHEEL
s4sdk-0.2.1a2.dist-info/METADATA
s4sdk-0.2.1a2.dist-info/RECORD
