Metadata-Version: 2.1
Name: s4sdk
Version: 0.2.1a2
Summary: 
Author: Roy Chotechuang
Author-email: htraexd@gmail.com
Requires-Python: >=3.10,<4.0
Classifier: Programming Language :: Python :: 3
Classifier: Programming Language :: Python :: 3.10
Requires-Dist: PyYAML (>=6.0,<7.0)
Requires-Dist: argparse (>=1.4.0,<2.0.0)
Requires-Dist: click (>=8.1.3,<9.0.0)
Requires-Dist: pandas (>=1.4.3,<2.0.0)
